margo_loader/__init__.py
margo_loader/nbfinder.py
margo_loader/nbloader.py
margo_loader/processor.py
margo_loader/cli/__init__.py
margo_loader/cli/__main__.py
margo_loader/cli/commands/__init__.py
margo_loader/cli/commands/extract.py
margo_loader/cli/commands/makefile.py
margo_loader/utils/__init__.py
margo_loader/utils/get_cells/FakeCell.py
margo_loader/utils/get_cells/__init__.py
margo_loader/utils/get_cells/get_cells.py
margo_loader/utils/get_cells/get_ipynb_cells.py
margo_loader/utils/get_cells/get_nbpy_cells.py
margo_loader/utils/resolve_path/LEGACY_find_notebook.py
margo_loader/utils/resolve_path/__init__.py
margo_loader/utils/resolve_path/resolve_path.py
margo_loader-1.0.4.dist-info/METADATA
margo_loader-1.0.4.dist-info/WHEEL
margo_loader-1.0.4.dist-info/entry_points.txt
margo_loader-1.0.4.dist-info/RECORD
