Metadata-Version: 2.1
Name: margo-loader
Version: 1.0.4
Summary: Import Jupyter notebooks using Margo notebook margin notebook syntax
Project-URL: Homepage, https://github.com/margo-notebooks/margo-loader-py
Project-URL: Bug Tracker, https://github.com/margo-notebooks/margo-loader-py/issues
Author-email: Jake Kara <jake@jakekara.com>
Classifier: License :: OSI Approved :: GNU General Public License v3 (GPLv3)
Classifier: Operating System :: OS Independent
Classifier: Programming Language :: Python :: 3
Requires-Python: >=3.6
Requires-Dist: margo-parser<2,>=1
Requires-Dist: nbformat<6,>5
